Topsis_Arjun_Angirus_102303596/__init__.py
Topsis_Arjun_Angirus_102303596/topsis.py
topsis_arjun_angirus_102303596-0.1.1.dist-info/licenses/LICENSE.txt
topsis_arjun_angirus_102303596-0.1.1.dist-info/METADATA
topsis_arjun_angirus_102303596-0.1.1.dist-info/WHEEL
topsis_arjun_angirus_102303596-0.1.1.dist-info/entry_points.txt
topsis_arjun_angirus_102303596-0.1.1.dist-info/top_level.txt
topsis_arjun_angirus_102303596-0.1.1.dist-info/RECORD
