Metadata-Version: 2.4
Name: Topsis_Arjun_Angirus_102303596
Version: 0.1.1
Summary: TOPSIS (Technique for Order Preference by Similarity to Ideal Solution) implementation for MCDM
Home-page: https://github.com/EarnTHYPart/Topsis-Arjun-Angirus-102303596
Download-URL: https://github.com/EarnTHYPart/Topsis-Arjun-Angirus-102303596/archive/refs/tags/v0.1.1.tar.gz
Author: Arjun Angirus
License: MIT
Project-URL: Source, https://github.com/EarnTHYPart/Topsis-Arjun-Angirus-102303596
Project-URL: Issues, https://github.com/EarnTHYPart/Topsis-Arjun-Angirus-102303596/issues
Classifier: Programming Language :: Python :: 3
Classifier: License :: OSI Approved :: MIT License
Classifier: Operating System :: OS Independent
Requires-Python: >=3.8
License-File: LICENSE.txt
Requires-Dist: numpy>=1.26.0
Requires-Dist: pandas>=2.0.0
Dynamic: download-url
Dynamic: license-file
